og_nav/README.md
og_nav/__init__.py
og_nav/_version.py
og_nav/assets/Custom_Robot_Description_Development_Guide.md
og_nav/assets/OGM_img.png
og_nav/assets/TiagoRobotDescriptionProject_Analysis.md
og_nav/assets/map.png
og_nav/assets/path_tracking_results_20250710_153212.png
og_nav/assets/tiago_controller_analysis.md
og_nav/configs/config.example.yaml
og_nav/configs/navigation_config.yaml
og_nav/control/__init__.py
og_nav/control/arrival_state.py
og_nav/control/control_utils.py
og_nav/control/controllers.py
og_nav/core/__init__.py
og_nav/core/config_loader.py
og_nav/core/constants.py
og_nav/core/navigation.py
og_nav/demos/__init__.py
og_nav/demos/navigation_demo.py
og_nav/mapping/__init__.py
og_nav/mapping/occupancy_grid.py
og_nav/ogm_cv2_window/__init__.py
og_nav/ogm_cv2_window/ui.py
og_nav/planning/__init__.py
og_nav/planning/path_planning.py
og_nav/planning/utils.py
og_nav-0.1.1.dev0.dist-info/METADATA
og_nav-0.1.1.dev0.dist-info/WHEEL
og_nav-0.1.1.dev0.dist-info/top_level.txt
og_nav-0.1.1.dev0.dist-info/RECORD
