Metadata-Version: 2.4
Name: og_nav
Version: 0.1.1.dev0
Summary: A modular navigation system for robot navigation in OmniGibson environments.
Author-email: Litian Gong <gonglitian2002@gmail.com>
License: MIT
Project-URL: Homepage, https://github.com/Gonglitian/og_nav
Project-URL: Repository, https://github.com/Gonglitian/og_nav
Keywords: robotics,navigation,omnigibson,path-planning,robot-control
Classifier: Development Status :: 4 - Beta
Classifier: Intended Audience :: Science/Research
Classifier: Intended Audience :: Developers
Classifier: License :: OSI Approved :: MIT License
Classifier: Programming Language :: Python :: 3
Classifier: Programming Language :: Python :: 3.8
Classifier: Programming Language :: Python :: 3.9
Classifier: Programming Language :: Python :: 3.10
Classifier: Programming Language :: Python :: 3.11
Classifier: Topic :: Scientific/Engineering :: Artificial Intelligence
Classifier: Topic :: Software Development :: Libraries :: Python Modules
Requires-Python: >=3.8
Requires-Dist: omnigibson
Requires-Dist: torch
Requires-Dist: numpy
Requires-Dist: opencv-python
Requires-Dist: matplotlib
Requires-Dist: pyyaml
